Metadata-Version: 2.1
Name: f6-core
Version: 1.0.4
Summary: The "F6" program is a program designed to work with electronic      paper accounting of attendance and academic performance of students of secondary professional      organizations, which generates reports in the form of an extract – "Form 6".
Home-page: UNKNOWN
Author-email: ivan666999z@outlook.com
License: UNKNOWN
Keywords: f6,f6_core
Platform: UNKNOWN
Classifier: License :: OSI Approved :: Apache Software License
Classifier: Intended Audience :: Developers
Classifier: Programming Language :: Python :: 3 :: Only
License-File: LICENSE
